{
  "currentRound":149,
  "maxRounds":600,
  "player":{
    "id":1,
    "position":{
      "y":2,
      "x":1147
    },
    "speed":9,
    "state":"USED_BOOST",
    "statesThatOccurredThisRound":[
      "USED_BOOST"
    ],
    "powerups":[
      "EMP",
      "EMP",
      "EMP",
      "EMP",
      "EMP",
      "EMP",
      "EMP",
      "EMP",
      "EMP",
      "EMP",
      "EMP",
      "EMP",
      "EMP",
      "EMP",
      "BOOST"
    ],
    "boosting":true,
    "boostCounter":5,
    "damage":1,
    "score":270
  },
  "opponent":{
    "id":2,
    "position":{
      "y":2,
      "x":966
    },
    "speed":9
  },
  "worldMap":[
    [
      {
        "position":{
          "y":1,
          "x":1142
        },
        "surfaceObject":0,
        "occupiedByPlayerId":0,
        "isOccupiedByCyberTruck":false
      },
      {
        "position":{
          "y":1,
          "x":1143
        },
        "surfaceObject":0,
        "occupiedByPlayerId":0,
        "isOccupiedByCyberTruck":false
      },
      {
        "position":{
          "y":1,
          "x":1144
        },
        "surfaceObject":0,
        "occupiedByPlayerId":0,
        "isOccupiedByCyberTruck":false
      },
      {
        "position":{
          "y":1,
          "x":1145
        },
        "surfaceObject":0,
        "occupiedByPlayerId":0,
        "isOccupiedByCyberTruck":false
      },
      {
        "position":{
          "y":1,
          "x":1146
        },
        "surfaceObject":0,
        "occupiedByPlayerId":0,
        "isOccupiedByCyberTruck":false
      },
      {
        "position":{
          "y":1,
          "x":1147
        },
        "surfaceObject":5,
        "occupiedByPlayerId":0,
        "isOccupiedByCyberTruck":false
      },
      {
        "position":{
          "y":1,
          "x":1148
        },
        "surfaceObject":6,
        "occupiedByPlayerId":0,
        "isOccupiedByCyberTruck":false
      },
      {
        "position":{
          "y":1,
          "x":1149
        },
        "surfaceObject":0,
        "occupiedByPlayerId":0,
        "isOccupiedByCyberTruck":false
      },
      {
        "position":{
          "y":1,
          "x":1150
        },
        "surfaceObject":1,
        "occupiedByPlayerId":0,
        "isOccupiedByCyberTruck":false
      },
      {
        "position":{
          "y":1,
          "x":1151
        },
        "surfaceObject":1,
        "occupiedByPlayerId":0,
        "isOccupiedByCyberTruck":false
      },
      {
        "position":{
          "y":1,
          "x":1152
        },
        "surfaceObject":0,
        "occupiedByPlayerId":0,
        "isOccupiedByCyberTruck":false
      },
      {
        "position":{
          "y":1,
          "x":1153
        },
        "surfaceObject":0,
        "occupiedByPlayerId":0,
        "isOccupiedByCyberTruck":false
      },
      {
        "position":{
          "y":1,
          "x":1154
        },
        "surfaceObject":0,
        "occupiedByPlayerId":0,
        "isOccupiedByCyberTruck":false
      },
      {
        "position":{
          "y":1,
          "x":1155
        },
        "surfaceObject":0,
        "occupiedByPlayerId":0,
        "isOccupiedByCyberTruck":false
      },
      {
        "position":{
          "y":1,
          "x":1156
        },
        "surfaceObject":0,
        "occupiedByPlayerId":0,
        "isOccupiedByCyberTruck":false
      },
      {
        "position":{
          "y":1,
          "x":1157
        },
        "surfaceObject":0,
        "occupiedByPlayerId":0,
        "isOccupiedByCyberTruck":false
      },
      {
        "position":{
          "y":1,
          "x":1158
        },
        "surfaceObject":0,
        "occupiedByPlayerId":0,
        "isOccupiedByCyberTruck":false
      },
      {
        "position":{
          "y":1,
          "x":1159
        },
        "surfaceObject":0,
        "occupiedByPlayerId":0,
        "isOccupiedByCyberTruck":false
      },
      {
        "position":{
          "y":1,
          "x":1160
        },
        "surfaceObject":0,
        "occupiedByPlayerId":0,
        "isOccupiedByCyberTruck":false
      },
      {
        "position":{
          "y":1,
          "x":1161
        },
        "surfaceObject":0,
        "occupiedByPlayerId":0,
        "isOccupiedByCyberTruck":false
      },
      {
        "position":{
          "y":1,
          "x":1162
        },
        "surfaceObject":0,
        "occupiedByPlayerId":0,
        "isOccupiedByCyberTruck":false
      },
      {
        "position":{
          "y":1,
          "x":1163
        },
        "surfaceObject":0,
        "occupiedByPlayerId":0,
        "isOccupiedByCyberTruck":false
      },
      {
        "position":{
          "y":1,
          "x":1164
        },
        "surfaceObject":0,
        "occupiedByPlayerId":0,
        "isOccupiedByCyberTruck":false
      },
      {
        "position":{
          "y":1,
          "x":1165
        },
        "surfaceObject":5,
        "occupiedByPlayerId":0,
        "isOccupiedByCyberTruck":false
      },
      {
        "position":{
          "y":1,
          "x":1166
        },
        "surfaceObject":0,
        "occupiedByPlayerId":0,
        "isOccupiedByCyberTruck":false
      },
      {
        "position":{
          "y":1,
          "x":1167
        },
        "surfaceObject":0,
        "occupiedByPlayerId":0,
        "isOccupiedByCyberTruck":false
      }
    ],
    [
      {
        "position":{
          "y":2,
          "x":1142
        },
        "surfaceObject":0,
        "occupiedByPlayerId":0,
        "isOccupiedByCyberTruck":false
      },
      {
        "position":{
          "y":2,
          "x":1143
        },
        "surfaceObject":0,
        "occupiedByPlayerId":0,
        "isOccupiedByCyberTruck":false
      },
      {
        "position":{
          "y":2,
          "x":1144
        },
        "surfaceObject":0,
        "occupiedByPlayerId":0,
        "isOccupiedByCyberTruck":false
      },
      {
        "position":{
          "y":2,
          "x":1145
        },
        "surfaceObject":0,
        "occupiedByPlayerId":0,
        "isOccupiedByCyberTruck":false
      },
      {
        "position":{
          "y":2,
          "x":1146
        },
        "surfaceObject":0,
        "occupiedByPlayerId":0,
        "isOccupiedByCyberTruck":false
      },
      {
        "position":{
          "y":2,
          "x":1147
        },
        "surfaceObject":0,
        "occupiedByPlayerId":1,
        "isOccupiedByCyberTruck":false
      },
      {
        "position":{
          "y":2,
          "x":1148
        },
        "surfaceObject":0,
        "occupiedByPlayerId":0,
        "isOccupiedByCyberTruck":false
      },
      {
        "position":{
          "y":2,
          "x":1149
        },
        "surfaceObject":0,
        "occupiedByPlayerId":0,
        "isOccupiedByCyberTruck":false
      },
      {
        "position":{
          "y":2,
          "x":1150
        },
        "surfaceObject":0,
        "occupiedByPlayerId":0,
        "isOccupiedByCyberTruck":false
      },
      {
        "position":{
          "y":2,
          "x":1151
        },
        "surfaceObject":0,
        "occupiedByPlayerId":0,
        "isOccupiedByCyberTruck":false
      },
      {
        "position":{
          "y":2,
          "x":1152
        },
        "surfaceObject":0,
        "occupiedByPlayerId":0,
        "isOccupiedByCyberTruck":false
      },
      {
        "position":{
          "y":2,
          "x":1153
        },
        "surfaceObject":8,
        "occupiedByPlayerId":0,
        "isOccupiedByCyberTruck":false
      },
      {
        "position":{
          "y":2,
          "x":1154
        },
        "surfaceObject":0,
        "occupiedByPlayerId":0,
        "isOccupiedByCyberTruck":false
      },
      {
        "position":{
          "y":2,
          "x":1155
        },
        "surfaceObject":0,
        "occupiedByPlayerId":0,
        "isOccupiedByCyberTruck":false
      },
      {
        "position":{
          "y":2,
          "x":1156
        },
        "surfaceObject":0,
        "occupiedByPlayerId":0,
        "isOccupiedByCyberTruck":false
      },
      {
        "position":{
          "y":2,
          "x":1157
        },
        "surfaceObject":0,
        "occupiedByPlayerId":0,
        "isOccupiedByCyberTruck":false
      },
      {
        "position":{
          "y":2,
          "x":1158
        },
        "surfaceObject":0,
        "occupiedByPlayerId":0,
        "isOccupiedByCyberTruck":false
      },
      {
        "position":{
          "y":2,
          "x":1159
        },
        "surfaceObject":0,
        "occupiedByPlayerId":0,
        "isOccupiedByCyberTruck":false
      },
      {
        "position":{
          "y":2,
          "x":1160
        },
        "surfaceObject":0,
        "occupiedByPlayerId":0,
        "isOccupiedByCyberTruck":false
      },
      {
        "position":{
          "y":2,
          "x":1161
        },
        "surfaceObject":0,
        "occupiedByPlayerId":0,
        "isOccupiedByCyberTruck":false
      },
      {
        "position":{
          "y":2,
          "x":1162
        },
        "surfaceObject":0,
        "occupiedByPlayerId":0,
        "isOccupiedByCyberTruck":false
      },
      {
        "position":{
          "y":2,
          "x":1163
        },
        "surfaceObject":0,
        "occupiedByPlayerId":0,
        "isOccupiedByCyberTruck":false
      },
      {
        "position":{
          "y":2,
          "x":1164
        },
        "surfaceObject":0,
        "occupiedByPlayerId":0,
        "isOccupiedByCyberTruck":false
      },
      {
        "position":{
          "y":2,
          "x":1165
        },
        "surfaceObject":0,
        "occupiedByPlayerId":0,
        "isOccupiedByCyberTruck":false
      },
      {
        "position":{
          "y":2,
          "x":1166
        },
        "surfaceObject":5,
        "occupiedByPlayerId":0,
        "isOccupiedByCyberTruck":false
      },
      {
        "position":{
          "y":2,
          "x":1167
        },
        "surfaceObject":0,
        "occupiedByPlayerId":0,
        "isOccupiedByCyberTruck":false
      }
    ],
    [
      {
        "position":{
          "y":3,
          "x":1142
        },
        "surfaceObject":0,
        "occupiedByPlayerId":0,
        "isOccupiedByCyberTruck":false
      },
      {
        "position":{
          "y":3,
          "x":1143
        },
        "surfaceObject":0,
        "occupiedByPlayerId":0,
        "isOccupiedByCyberTruck":false
      },
      {
        "position":{
          "y":3,
          "x":1144
        },
        "surfaceObject":0,
        "occupiedByPlayerId":0,
        "isOccupiedByCyberTruck":false
      },
      {
        "position":{
          "y":3,
          "x":1145
        },
        "surfaceObject":0,
        "occupiedByPlayerId":0,
        "isOccupiedByCyberTruck":false
      },
      {
        "position":{
          "y":3,
          "x":1146
        },
        "surfaceObject":0,
        "occupiedByPlayerId":0,
        "isOccupiedByCyberTruck":false
      },
      {
        "position":{
          "y":3,
          "x":1147
        },
        "surfaceObject":0,
        "occupiedByPlayerId":0,
        "isOccupiedByCyberTruck":false
      },
      {
        "position":{
          "y":3,
          "x":1148
        },
        "surfaceObject":0,
        "occupiedByPlayerId":0,
        "isOccupiedByCyberTruck":false
      },
      {
        "position":{
          "y":3,
          "x":1149
        },
        "surfaceObject":0,
        "occupiedByPlayerId":0,
        "isOccupiedByCyberTruck":false
      },
      {
        "position":{
          "y":3,
          "x":1150
        },
        "surfaceObject":0,
        "occupiedByPlayerId":0,
        "isOccupiedByCyberTruck":false
      },
      {
        "position":{
          "y":3,
          "x":1151
        },
        "surfaceObject":0,
        "occupiedByPlayerId":0,
        "isOccupiedByCyberTruck":false
      },
      {
        "position":{
          "y":3,
          "x":1152
        },
        "surfaceObject":0,
        "occupiedByPlayerId":0,
        "isOccupiedByCyberTruck":false
      },
      {
        "position":{
          "y":3,
          "x":1153
        },
        "surfaceObject":0,
        "occupiedByPlayerId":0,
        "isOccupiedByCyberTruck":false
      },
      {
        "position":{
          "y":3,
          "x":1154
        },
        "surfaceObject":0,
        "occupiedByPlayerId":0,
        "isOccupiedByCyberTruck":false
      },
      {
        "position":{
          "y":3,
          "x":1155
        },
        "surfaceObject":0,
        "occupiedByPlayerId":0,
        "isOccupiedByCyberTruck":false
      },
      {
        "position":{
          "y":3,
          "x":1156
        },
        "surfaceObject":0,
        "occupiedByPlayerId":0,
        "isOccupiedByCyberTruck":false
      },
      {
        "position":{
          "y":3,
          "x":1157
        },
        "surfaceObject":0,
        "occupiedByPlayerId":0,
        "isOccupiedByCyberTruck":false
      },
      {
        "position":{
          "y":3,
          "x":1158
        },
        "surfaceObject":0,
        "occupiedByPlayerId":0,
        "isOccupiedByCyberTruck":false
      },
      {
        "position":{
          "y":3,
          "x":1159
        },
        "surfaceObject":0,
        "occupiedByPlayerId":0,
        "isOccupiedByCyberTruck":false
      },
      {
        "position":{
          "y":3,
          "x":1160
        },
        "surfaceObject":0,
        "occupiedByPlayerId":0,
        "isOccupiedByCyberTruck":false
      },
      {
        "position":{
          "y":3,
          "x":1161
        },
        "surfaceObject":0,
        "occupiedByPlayerId":0,
        "isOccupiedByCyberTruck":false
      },
      {
        "position":{
          "y":3,
          "x":1162
        },
        "surfaceObject":0,
        "occupiedByPlayerId":0,
        "isOccupiedByCyberTruck":false
      },
      {
        "position":{
          "y":3,
          "x":1163
        },
        "surfaceObject":0,
        "occupiedByPlayerId":0,
        "isOccupiedByCyberTruck":false
      },
      {
        "position":{
          "y":3,
          "x":1164
        },
        "surfaceObject":0,
        "occupiedByPlayerId":0,
        "isOccupiedByCyberTruck":false
      },
      {
        "position":{
          "y":3,
          "x":1165
        },
        "surfaceObject":0,
        "occupiedByPlayerId":0,
        "isOccupiedByCyberTruck":false
      },
      {
        "position":{
          "y":3,
          "x":1166
        },
        "surfaceObject":7,
        "occupiedByPlayerId":0,
        "isOccupiedByCyberTruck":false
      },
      {
        "position":{
          "y":3,
          "x":1167
        },
        "surfaceObject":0,
        "occupiedByPlayerId":0,
        "isOccupiedByCyberTruck":false
      }
    ],
    [
      {
        "position":{
          "y":4,
          "x":1142
        },
        "surfaceObject":0,
        "occupiedByPlayerId":0,
        "isOccupiedByCyberTruck":false
      },
      {
        "position":{
          "y":4,
          "x":1143
        },
        "surfaceObject":5,
        "occupiedByPlayerId":0,
        "isOccupiedByCyberTruck":false
      },
      {
        "position":{
          "y":4,
          "x":1144
        },
        "surfaceObject":0,
        "occupiedByPlayerId":0,
        "isOccupiedByCyberTruck":false
      },
      {
        "position":{
          "y":4,
          "x":1145
        },
        "surfaceObject":6,
        "occupiedByPlayerId":0,
        "isOccupiedByCyberTruck":false
      },
      {
        "position":{
          "y":4,
          "x":1146
        },
        "surfaceObject":0,
        "occupiedByPlayerId":0,
        "isOccupiedByCyberTruck":false
      },
      {
        "position":{
          "y":4,
          "x":1147
        },
        "surfaceObject":0,
        "occupiedByPlayerId":0,
        "isOccupiedByCyberTruck":false
      },
      {
        "position":{
          "y":4,
          "x":1148
        },
        "surfaceObject":0,
        "occupiedByPlayerId":0,
        "isOccupiedByCyberTruck":false
      },
      {
        "position":{
          "y":4,
          "x":1149
        },
        "surfaceObject":0,
        "occupiedByPlayerId":0,
        "isOccupiedByCyberTruck":false
      },
      {
        "position":{
          "y":4,
          "x":1150
        },
        "surfaceObject":0,
        "occupiedByPlayerId":0,
        "isOccupiedByCyberTruck":false
      },
      {
        "position":{
          "y":4,
          "x":1151
        },
        "surfaceObject":0,
        "occupiedByPlayerId":0,
        "isOccupiedByCyberTruck":false
      },
      {
        "position":{
          "y":4,
          "x":1152
        },
        "surfaceObject":0,
        "occupiedByPlayerId":0,
        "isOccupiedByCyberTruck":false
      },
      {
        "position":{
          "y":4,
          "x":1153
        },
        "surfaceObject":0,
        "occupiedByPlayerId":0,
        "isOccupiedByCyberTruck":false
      },
      {
        "position":{
          "y":4,
          "x":1154
        },
        "surfaceObject":0,
        "occupiedByPlayerId":0,
        "isOccupiedByCyberTruck":false
      },
      {
        "position":{
          "y":4,
          "x":1155
        },
        "surfaceObject":0,
        "occupiedByPlayerId":0,
        "isOccupiedByCyberTruck":false
      },
      {
        "position":{
          "y":4,
          "x":1156
        },
        "surfaceObject":0,
        "occupiedByPlayerId":0,
        "isOccupiedByCyberTruck":false
      },
      {
        "position":{
          "y":4,
          "x":1157
        },
        "surfaceObject":0,
        "occupiedByPlayerId":0,
        "isOccupiedByCyberTruck":false
      },
      {
        "position":{
          "y":4,
          "x":1158
        },
        "surfaceObject":0,
        "occupiedByPlayerId":0,
        "isOccupiedByCyberTruck":false
      },
      {
        "position":{
          "y":4,
          "x":1159
        },
        "surfaceObject":0,
        "occupiedByPlayerId":0,
        "isOccupiedByCyberTruck":false
      },
      {
        "position":{
          "y":4,
          "x":1160
        },
        "surfaceObject":0,
        "occupiedByPlayerId":0,
        "isOccupiedByCyberTruck":false
      },
      {
        "position":{
          "y":4,
          "x":1161
        },
        "surfaceObject":0,
        "occupiedByPlayerId":0,
        "isOccupiedByCyberTruck":false
      },
      {
        "position":{
          "y":4,
          "x":1162
        },
        "surfaceObject":0,
        "occupiedByPlayerId":0,
        "isOccupiedByCyberTruck":false
      },
      {
        "position":{
          "y":4,
          "x":1163
        },
        "surfaceObject":0,
        "occupiedByPlayerId":0,
        "isOccupiedByCyberTruck":false
      },
      {
        "position":{
          "y":4,
          "x":1164
        },
        "surfaceObject":0,
        "occupiedByPlayerId":0,
        "isOccupiedByCyberTruck":false
      },
      {
        "position":{
          "y":4,
          "x":1165
        },
        "surfaceObject":0,
        "occupiedByPlayerId":0,
        "isOccupiedByCyberTruck":false
      },
      {
        "position":{
          "y":4,
          "x":1166
        },
        "surfaceObject":0,
        "occupiedByPlayerId":0,
        "isOccupiedByCyberTruck":false
      },
      {
        "position":{
          "y":4,
          "x":1167
        },
        "surfaceObject":0,
        "occupiedByPlayerId":0,
        "isOccupiedByCyberTruck":false
      }
    ]
  ]
}